giddy/__init__.py
giddy/components.py
giddy/directional.py
giddy/ergodic.py
giddy/markov.py
giddy/mobility.py
giddy/plotting.py
giddy/rank.py
giddy/sequence.py
giddy/util.py
giddy/tests/__init__.py
giddy/tests/test_directional.py
giddy/tests/test_ergodic.py
giddy/tests/test_markov.py
giddy/tests/test_mobility.py
giddy/tests/test_plotting.py
giddy/tests/test_rank.py
giddy/tests/test_sequence.py
giddy/tests/test_util.py
giddy-2.3.8.dist-info/licenses/LICENSE.txt
giddy-2.3.8.dist-info/METADATA
giddy-2.3.8.dist-info/WHEEL
giddy-2.3.8.dist-info/top_level.txt
giddy-2.3.8.dist-info/RECORD
