Metadata-Version: 2.4
Name: giddy
Version: 2.3.8
Summary: PySAL-giddy for exploratory spatiotemporal data analysis
Maintainer-email: Wei Kang <weikang9009@gmail.com>
License: BSD 3-Clause
Project-URL: Home, https://pysal.org/giddy/
Project-URL: Repository, https://github.com/pysal/giddy
Keywords: spatial statistics,spatiotemporal analysis
Classifier: Programming Language :: Python :: 3
Classifier: License :: OSI Approved :: BSD License
Classifier: Operating System :: OS Independent
Classifier: Intended Audience :: Science/Research
Classifier: Topic :: Scientific/Engineering :: GIS
Requires-Python: >=3.11
License-File: LICENSE.txt
Requires-Dist: esda<2.9,>=2.7
Requires-Dist: libpysal>=4.12
Requires-Dist: mapclassify>=2.7
Requires-Dist: quantecon>=0.8
Requires-Dist: scipy>=1.12
Requires-Dist: seaborn
Requires-Dist: matplotlib
Provides-Extra: dev
Requires-Dist: ruff; extra == "dev"
Requires-Dist: pre-commit; extra == "dev"
Provides-Extra: docs
Requires-Dist: nbsphinx; extra == "docs"
Requires-Dist: numpydoc; extra == "docs"
Requires-Dist: sphinx; extra == "docs"
Requires-Dist: sphinxcontrib-bibtex; extra == "docs"
Requires-Dist: sphinx_bootstrap_theme; extra == "docs"
Provides-Extra: tests
Requires-Dist: codecov; extra == "tests"
Requires-Dist: ipywidgets; extra == "tests"
Requires-Dist: pytest; extra == "tests"
Requires-Dist: pytest-cov; extra == "tests"
Requires-Dist: pytest-xdist; extra == "tests"
Dynamic: license-file
